{"ALB": {"2009": 8.4}, "ARM": {"2005": 9.6}, "AZE": {"2006": 5.7}, "BGD": {"1997": 24.3}, "BEN": {"1996": 21.8, "2001": 21.9, "2006": 19.4}, "BOL": {"1998": 14.5, "2003": 16.2, "2008": 16.5}, "BRA": {"1996": 4.2}, "BFA": {"1999": 23.2, "2003": 26.9}, "CMR": {"1998": 19.2}, "CAF": {"1995": 35.3}, "TCD": {"1997": 49.2, "2004": 43.1}, "COM": {"1996": 13.1}, "COG": {"2005": 3.6}, "CIV": {"1999": 11.1}, "COD": {"2007": 14.5}, "DOM": {"1996": 5.9}, "ERI": {"1995": 35.2}, "ETH": {"2005": 42.6}, "GAB": {"2000": 2}, "GHA": {"1998": 10.7, "2003": 11.3, "2008": 13.9}, "GIN": {"1999": 22.6, "2005": 21.5}, "GUY": {"2009": 4}, "HTI": {"2000": 13.1}, "IDN": {"2003": 18.8, "2007": 19.1}, "KAZ": {"1999": 1.4}, "KEN": {"1998": 10.6, "2003": 8.3, "2009": 11.2}, "LSO": {"2004": 3, "2009": 6.1}, "LBR": {"2007": 15}, "MDG": {"2004": 27.9, "2009": 37.8}, "MWI": {"2000": 19.2, "2004": 22.7, "2010": 21.8}, "MLI": {"1996": 19.5, "2001": 18.4}, "MRT": {"2001": 7.8}, "MOZ": {"1997": 30.9}, "NAM": {"2000": 0.8, "2007": 1.5}, "NPL": {"2001": 48, "2006": 21}, "NIC": {"1998": 10.7}, "NER": {"1998": 31.8, "2006": 20.6}, "NGA": {"1999": 16.2, "2003": 13.8, "2008": 18.5}, "PER": {"1996": 11}, "PHL": {"2003": 6.1}, "RWA": {"2005": 13.8}, "SEN": {"2005": 6.8}, "SLE": {"2008": 21.8}, "SWZ": {"2007": 0.8}, "TZA": {"1999": 26.6, "2005": 30.6}, "TLS": {"2010": 53.7}, "TGO": {"1998": 7.9}, "TUR": {"1998": 6}, "UGA": {"1995": 26.4, "2001": 26.2, "2006": 24.6}, "UKR": {"2007": 0.5}, "ZMB": {"1996": 16.4, "2002": 25.3, "2007": 24}
}
