{"ARM": {"2003": 5.8}, "BEN": {"2003": 49.5}, "BTN": {"2003": 33.8}, "BOL": {"2002": 25.6, "2005": 19.3}, "BRA": {"2008": 4.3}, "BFA": {"2003": 59.1}, "BDI": {"1998": 87.7}, "KHM": {"2004": 37.7}, "CMR": {"2001": 11.3}, "CPV": {"2002": 23.5}, "COL": {"2003": 24.1}, "COG": {"2005": 58.6}, "CIV": {"2002": 28.8}, "DOM": {"2000": 6}, "SLV": {"2003": 18.2}, "GAB": {"2005": 4.3}, "GHA": {"1998": 42.8}, "GTM": {"2000": 10.5, "2006": 14}, "GIN": {"2003": 68.6}, "IND": {"2005": 38.9, "2010": 32.4}, "IDN": {"2002": 32.6}, "JOR": {"2002": 1.2}, "KAZ": {"2003": 3.3}, "LSO": {"2002": 41.1}, "LBR": {"2007": 85.9}, "MDG": {"2005": 67.7}, "MWI": {"2004": 69.9}, "MLI": {"2006": 55.6}, "MEX": {"2004": 2.5}, "MAR": {"1998": 6.1}, "MOZ": {"2003": 69.1}, "NPL": {"2003": 48.4}, "NIC": {"1998": 14.3, "2001": 17.7, "2005": 14.9}, "NER": {"2005": 49}, "NGA": {"2004": 72.6}, "PAK": {"2005": 19}, "PAN": {"1997": 19.9}, "PRY": {"2002": 23}, "PER": {"2002": 13.9, "2006": 8.9}, "PHL": {"2003": 25.7}, "SEN": {"2001": 50}, "SLE": {"2003": 58.8}, "ZAF": {"2000": 17.1}, "LKA": {"2002": 15.6}, "TJK": {"2003": 34.9}, "THA": {"2002": 1.7}, "TLS": {"2001": 50.8}, "TGO": {"2006": 45.5}, "TUR": {"2002": 1.3}, "UGA": {"2005": 45.3}, "VNM": {"2004": 31.1, "2006": 24}, "ASE": {"2005": 28.95, "2010": 32.4}, "SAM": {"2005": 19, "2010": 32.4}, "SAE": {"2005": 31.0702, "2010": 24.1973}
}
